takeoff_client/__init__.py
takeoff_client/exceptions.py
takeoff_client/sse.py
takeoff_client/takeoff_client.py
takeoff_client-0.7.0.dist-info/METADATA
takeoff_client-0.7.0.dist-info/WHEEL
takeoff_client-0.7.0.dist-info/RECORD
