Metadata-Version: 2.4
Name: takeoff-client
Version: 0.7.0
Summary: Takeoff Client is a Python client for the Takeoff Server
Author-email: TitanML <hello@titanml.co>
Requires-Dist: httpx==0.27.0
Requires-Dist: sseclient-py>=1.8.0
Requires-Dist: takeoff-config>=0.5.1
